temmies/__init__.py
temmies/course.py
temmies/exercise_group.py
temmies/group.py
temmies/submission.py
temmies/themis.py
temmies/year.py
temmies/exceptions/__init__.py
temmies/exceptions/course_unavailable.py
temmies/exceptions/illegal_action.py
temmies/exceptions/session_expired.py
temmies-1.2.130.dist-info/licenses/LICENSE
temmies-1.2.130.dist-info/METADATA
temmies-1.2.130.dist-info/WHEEL
temmies-1.2.130.dist-info/top_level.txt
temmies-1.2.130.dist-info/RECORD
