Metadata-Version: 2.4
Name: temmies
Version: 1.2.130
Summary: A wrapper for the Themis website
Home-page: https://github.com/Code-For-Groningen/temmies
Author: Boyan K.
Author-email: boyan@confest.im
License: GPLv3
Classifier: Development Status :: 4 - Beta
Classifier: Intended Audience :: Developers
Classifier: License :: OSI Approved :: GNU General Public License v3 (GPLv3)
Classifier: Programming Language :: Python :: 3.9
Requires-Python: >=3.9
License-File: LICENSE
Requires-Dist: urllib3
Requires-Dist: requests
Requires-Dist: lxml
Requires-Dist: beautifulsoup4
Requires-Dist: keyring
Requires-Dist: selenium
Dynamic: author
Dynamic: author-email
Dynamic: classifier
Dynamic: description
Dynamic: description-content-type
Dynamic: home-page
Dynamic: license
Dynamic: license-file
Dynamic: requires-dist
Dynamic: requires-python
Dynamic: summary
